livekit_plugins_realtimestt/__init__.py
livekit_plugins_realtimestt/log.py
livekit_plugins_realtimestt/py.typed
livekit_plugins_realtimestt/stt.py
livekit_plugins_realtimestt/version.py
livekit_plugins_realtimestt-0.1.1.dist-info/METADATA
livekit_plugins_realtimestt-0.1.1.dist-info/WHEEL
livekit_plugins_realtimestt-0.1.1.dist-info/licenses/LICENSE
livekit_plugins_realtimestt-0.1.1.dist-info/RECORD
