Metadata-Version: 2.4
Name: livekit-plugins-realtimestt
Version: 0.1.1
Summary: RealtimeSTT plugin for LiveKit
Author-email: Alex Schneider <me@schneider.ax>
License: ISC License
License-File: LICENSE
Keywords: audio,livekit,realtime,speech-to-text,stream,stt,webrtc
Classifier: Intended Audience :: Developers
Classifier: Programming Language :: Python :: 3
Classifier: Programming Language :: Python :: 3 :: Only
Classifier: Programming Language :: Python :: 3.11
Classifier: Topic :: Multimedia :: Sound/Audio
Classifier: Topic :: Scientific/Engineering :: Artificial Intelligence
Requires-Python: >=3.11
Requires-Dist: livekit-agents>=1.0.14
Requires-Dist: livekit>=1.0.6
Requires-Dist: realtimestt>=0.3.103
